scanlog/__init__.py
scanlog/scanlog.py
scanlog-1.0.2.dist-info/LICENSE
scanlog-1.0.2.dist-info/METADATA
scanlog-1.0.2.dist-info/WHEEL
scanlog-1.0.2.dist-info/top_level.txt
scanlog-1.0.2.dist-info/RECORD
