Metadata-Version: 2.1
Name: scanlog
Version: 1.0.2
Summary: A common quantum chemistry files parser on top of cclib
Home-page: https://github.com/QuChemPedIA/scanlog
Author: Benoit Da Mota
Author-email: benoit.damota@univ-angers.fr
License: UNKNOWN
Project-URL: Bug Tracker, https://github.com/QuChemPedIA/scanlog/issues
Platform: UNKNOWN
Classifier: Programming Language :: Python :: 3
Classifier: License :: OSI Approved :: MIT License
Classifier: Operating System :: OS Independent
Requires-Python: >=3.4
License-File: LICENSE
